energoton/__init__.py
energoton/base/__init__.py
energoton/base/base.py
energoton/energoton/__init__.py
energoton/energoton/energoton.py
energoton/planner/__init__.py
energoton/planner/planner.py
energoton/relation/__init__.py
energoton/relation/relation.py
energoton/work/__init__.py
energoton/work/pool.py
energoton/work/task.py
energoton/work/work_unit.py
energoton-0.2.dist-info/licenses/LICENSE.md
energoton-0.2.dist-info/METADATA
energoton-0.2.dist-info/WHEEL
energoton-0.2.dist-info/top_level.txt
energoton-0.2.dist-info/RECORD
