Metadata-Version: 2.4
Name: energoton
Version: 0.2
Summary: Automated task planning package
Home-page: https://github.com/IlyaFaer/energoton_py/
Author: IlyaFaer
Author-email: ilya.faer.gurov@gmail.com
License-File: LICENSE.md
Dynamic: author
Dynamic: author-email
Dynamic: description
Dynamic: description-content-type
Dynamic: home-page
Dynamic: license-file
Dynamic: summary
